torchnlp/__init__.py
torchnlp-0.0.0.1.dist-info/LICENSE
torchnlp-0.0.0.1.dist-info/METADATA
torchnlp-0.0.0.1.dist-info/WHEEL
torchnlp-0.0.0.1.dist-info/top_level.txt
torchnlp-0.0.0.1.dist-info/RECORD
